pystk2_data/__init__.py
pystk2_data/setup.py
PySuperTuxKart2_Data-0.0.0.dist-info/METADATA
PySuperTuxKart2_Data-0.0.0.dist-info/WHEEL
PySuperTuxKart2_Data-0.0.0.dist-info/top_level.txt
PySuperTuxKart2_Data-0.0.0.dist-info/RECORD
